nrx/__about__.py
nrx/__init__.py
nrx/nrx.py
nrx-0.8.2.dist-info/METADATA
nrx-0.8.2.dist-info/WHEEL
nrx-0.8.2.dist-info/entry_points.txt
nrx-0.8.2.dist-info/licenses/LICENSE
nrx-0.8.2.dist-info/RECORD
