Metadata-Version: 2.4
Name: nrx
Version: 0.8.2
Summary: nrx - netreplica exporter
Project-URL: Homepage, https://github.com/netreplica/nrx
Project-URL: Issues, https://github.com/netreplica/nrx/issues
Author-email: Alex Bortok and Netreplica Team <dev@netreplica.com>
License:                                  Apache License
License-File: LICENSE
Classifier: License :: OSI Approved :: Apache Software License
Classifier: Operating System :: OS Independent
Classifier: Programming Language :: Python :: 3
Requires-Python: >=3.10
Requires-Dist: certifi
Requires-Dist: charset-normalizer>=3.4.2
Requires-Dist: idna>=3.10
Requires-Dist: jinja2>=3.1.6
Requires-Dist: markupsafe>=3.0.2
Requires-Dist: networkx>=3.4.2
Requires-Dist: pynetbox>=7.5.0
Requires-Dist: pyyaml>=6.0.2
Requires-Dist: requests>=2.32.3
Requires-Dist: toml>=0.10.2
Requires-Dist: urllib3>=2.4.0
